MANIFEST.in
README.txt
setup.py
simplenlp/__init__.py
simplenlp/euro.py
simplenlp/trie.py
simplenlp.egg-info/PKG-INFO
simplenlp.egg-info/SOURCES.txt
simplenlp.egg-info/dependency_links.txt
simplenlp.egg-info/requires.txt
simplenlp.egg-info/top_level.txt
simplenlp/ar/__init__.py
simplenlp/de/__init__.py
simplenlp/de/stop.txt
simplenlp/de/stopwords-de.txt
simplenlp/default/__init__.py
simplenlp/en/__init__.py
simplenlp/en/autocorrect.txt
simplenlp/en/blacklist.txt
simplenlp/en/frequencies.txt
simplenlp/en/stop.txt
simplenlp/en/swap4.txt
simplenlp/es/__init__.py
simplenlp/es/frequencies.txt
simplenlp/es/stop.txt
simplenlp/es/stopwords-es.txt
simplenlp/fi/__init__.py
simplenlp/fr/__init__.py
simplenlp/hu/__init__.py
simplenlp/hu/stop.txt
simplenlp/hu/stopwords-hu.txt
simplenlp/it/__init__.py
simplenlp/ja/__init__.py
simplenlp/ja_cabocha/README.txt
simplenlp/ja_cabocha/__init__.py
simplenlp/ja_cabocha/cabocha_token.py
simplenlp/ja_cabocha/chunk.py
simplenlp/ja_cabocha/debug.py
simplenlp/ja_cabocha/parser.py
simplenlp/ja_cabocha/properties.py
simplenlp/ja_cabocha/system.py
simplenlp/ja_cabocha/tree.py
simplenlp/ja_cabocha/util.py
simplenlp/ja_cabocha/utterance.py
simplenlp/ja_cabocha/word.py
simplenlp/ko/__init__.py
simplenlp/mblem/__init__.py
simplenlp/mblem/en.mblem.pickle
simplenlp/mblem/en.unlem.pickle
simplenlp/mblem/timbl_convert.py
simplenlp/mblem/train_unlem.py
simplenlp/mblem/trie.py
simplenlp/nl/__init__.py
simplenlp/nl/stop.txt
simplenlp/pt/__init__.py
simplenlp/pt/stop.txt
simplenlp/ru/__init__.py
simplenlp/ru/stop.txt
simplenlp/zh/__init__.py
test/test_nl_default.py
test/test_nl_euro.py
test/test_nl_ja.py
test/test_preprocess.py